{"cameraMode":{"drawMode":0,"name":"Shaded","section":"Shading Mode"},"sceneLighting":false,"audioPlay":false,"sceneViewState":{"m_AlwaysRefresh":false,"showFog":true,"showSkybox":false,"showFlares":true,"showImageEffects":true,"showParticleSystems":true,"showVisualEffectGraphs":true,"m_FxEnabled":true},"in2DMode":false,"pivot":{"x":26.114959716796876,"y":-10.961670875549317,"z":20.5339412689209},"rotation":{"x":-0.4352451264858246,"y":0.008003585040569306,"z":-0.006765753962099552,"w":-0.9010931253433228},"size":10.0,"orthographic":false}